{
  "name": "",
  "version": "",
  "description": "",
  "author": "",
  "license": "GPL-3.0",
  "main": "app.js",
  "scripts": {
    "test": "gulp lint"
  },
  "repository": {
    "type": "git",
    "url": ""
  },
  "dependencies": {
    "reekoh": "=1.0.2",
    "async": "=1.5.2",
    "lodash": "=4.11.1",
    "moment": "=2.13.0"
  },
  "devDependencies": {
    "gulp": "=3.9.1",
    "gulp-cli": "=1.2.1",
    "gulp-jshint": "=2.0.1",
    "gulp-json-lint": "=0.1.0",
    "gulp-mocha": "=2.2.0",
    "gulp-plumber": "=1.1.0",
    "gulp-standard": "=8.0.4",
    "jshint": "=2.9.4",
    "mocha": "=2.5.3",
    "should": "=9.0.2"
  }
}
